klio_cli/__init__.py
klio_cli/cli.py
klio_cli/options.py
klio_cli/commands/__init__.py
klio_cli/commands/base.py
klio_cli/commands/image/__init__.py
klio_cli/commands/image/build.py
klio_cli/commands/job/__init__.py
klio_cli/commands/job/audit.py
klio_cli/commands/job/configuration.py
klio_cli/commands/job/create.py
klio_cli/commands/job/delete.py
klio_cli/commands/job/gke.py
klio_cli/commands/job/profile.py
klio_cli/commands/job/run.py
klio_cli/commands/job/stop.py
klio_cli/commands/job/test.py
klio_cli/commands/job/verify.py
klio_cli/commands/job/utils/__init__.py
klio_cli/commands/job/utils/gcp_setup.py
klio_cli/commands/job/utils/templates/MANIFEST.in.tpl
klio_cli/commands/job/utils/templates/README.md.tpl
klio_cli/commands/job/utils/templates/dockerfile.tpl
klio_cli/commands/job/utils/templates/init.py.tpl
klio_cli/commands/job/utils/templates/job-requirements.txt.tpl
klio_cli/commands/job/utils/templates/klio-job-batch.yaml.tpl
klio_cli/commands/job/utils/templates/klio-job.yaml.tpl
klio_cli/commands/job/utils/templates/run.py.tpl
klio_cli/commands/job/utils/templates/setup.py.tpl
klio_cli/commands/job/utils/templates/test_transforms.py.tpl
klio_cli/commands/job/utils/templates/transforms-batch.py.tpl
klio_cli/commands/job/utils/templates/transforms.py.tpl
klio_cli/commands/message/__init__.py
klio_cli/commands/message/publish.py
klio_cli/utils/__init__.py
klio_cli/utils/cli_utils.py
klio_cli/utils/config_utils.py
klio_cli/utils/docker_utils.py
klio_cli/utils/multi_line_terminal_writer.py
klio_cli/utils/stackdriver_utils.py
klio_cli-22.3.0.dist-info/METADATA
klio_cli-22.3.0.dist-info/WHEEL
klio_cli-22.3.0.dist-info/entry_points.txt
klio_cli-22.3.0.dist-info/top_level.txt
klio_cli-22.3.0.dist-info/RECORD
