Metadata-Version: 2.1
Name: klio-cli
Version: 22.3.0
Summary: Main entrypoint for Klio jobs
Home-page: https://github.com/spotify/klio
Author: The klio developers
Author-email: opensource+klio@spotify.com
Maintainer: The klio developers
Maintainer-email: opensource+klio@spotify.com
License: UNKNOWN
Project-URL: Documentation, https://docs.klio.io
Project-URL: Bug Tracker, https://github.com/spotify/klio/issues
Project-URL: Source Code, https://github.com/spotify/klio
Keywords: klio,apache,beam,audio
Platform: UNKNOWN
Classifier: Development Status :: 3 - Alpha
Classifier: Natural Language :: English
Classifier: Operating System :: POSIX :: Linux
Classifier: Operating System :: MacOS :: MacOS X
Classifier: Programming Language :: Python
Classifier: Programming Language :: Python :: 3.6
Classifier: Programming Language :: Python :: 3.7
Classifier: Programming Language :: Python :: 3.8
Classifier: Programming Language :: Python :: Implementation :: CPython
Classifier: License :: OSI Approved :: Apache Software License
Classifier: Topic :: Software Development :: Libraries
Classifier: Topic :: Software Development :: Libraries :: Python Modules
Classifier: Topic :: Multimedia
Classifier: Topic :: Multimedia :: Graphics
Classifier: Topic :: Multimedia :: Sound/Audio
Classifier: Topic :: Multimedia :: Video
Classifier: Topic :: Scientific/Engineering
Classifier: Topic :: Scientific/Engineering :: Image Processing
Requires-Python: >=3.6, <3.9
Requires-Dist: click
Requires-Dist: dateparser
Requires-Dist: docker
Requires-Dist: emoji
Requires-Dist: glom
Requires-Dist: google-api-core
Requires-Dist: google-api-python-client
Requires-Dist: google-cloud-monitoring (>=2.0.0)
Requires-Dist: google-cloud-pubsub (>=2.0.0)
Requires-Dist: google-cloud-storage
Requires-Dist: jinja2
Requires-Dist: klio-core (>=22.3.0)
Requires-Dist: protobuf
Requires-Dist: pyyaml
Requires-Dist: setuptools
Provides-Extra: dev
Requires-Dist: sphinx ; extra == 'dev'
Requires-Dist: interrogate ; extra == 'dev'
Requires-Dist: coverage ; extra == 'dev'
Requires-Dist: kubernetes ; extra == 'dev'
Requires-Dist: mock ; extra == 'dev'
Requires-Dist: pytest (>=4.3.0) ; extra == 'dev'
Requires-Dist: pytest-cov ; extra == 'dev'
Requires-Dist: pytest-mock ; extra == 'dev'
Requires-Dist: klio-devtools ; extra == 'dev'
Requires-Dist: bumpversion ; extra == 'dev'
Requires-Dist: wheel ; extra == 'dev'
Provides-Extra: docs
Requires-Dist: sphinx ; extra == 'docs'
Requires-Dist: interrogate ; extra == 'docs'
Provides-Extra: kubernetes
Requires-Dist: kubernetes ; extra == 'kubernetes'
Provides-Extra: tests
Requires-Dist: coverage ; extra == 'tests'
Requires-Dist: kubernetes ; extra == 'tests'
Requires-Dist: mock ; extra == 'tests'
Requires-Dist: pytest (>=4.3.0) ; extra == 'tests'
Requires-Dist: pytest-cov ; extra == 'tests'
Requires-Dist: pytest-mock ; extra == 'tests'
